vimrunner
