Metadata-Version: 1.1
Name: vimrunner
Version: 1.0.3
Summary: Interface for controlling a Vim editor using Python code.
Home-page: https://github.com/andri-ch/vimrunner-python
Author: Andrei Chiver
Author-email: andreichiver@gmail.com
License: MIT
Keywords: test Vim editor server plugin
Platform: UNKNOWN
Classifier: Development Status :: 3 - Alpha
Classifier: Topic :: Software Development
Classifier: Programming Language :: Python :: 2.7
Classifier: Programming Language :: Python :: 3
Classifier: Programming Language :: Python :: 3.3
Classifier: License :: OSI Approved :: MIT License
